xiuxian_buff/__init__.py
xiuxian_buff/two_exp_cd.py
xiuxian_buff-0.30.dist-info/METADATA
xiuxian_buff-0.30.dist-info/WHEEL
xiuxian_buff-0.30.dist-info/top_level.txt
xiuxian_buff-0.30.dist-info/RECORD
